README.md
setup.py
wrds2postgres/__init__.py
wrds2postgres/wrds2postgres.py
wrds2postgres.egg-info/PKG-INFO
wrds2postgres.egg-info/SOURCES.txt
wrds2postgres.egg-info/dependency_links.txt
wrds2postgres.egg-info/requires.txt
wrds2postgres.egg-info/top_level.txt