Metadata-Version: 2.1
Name: wrds2postgres
Version: 0.0.5
Summary: Import WRDS tables or SAS data into PostgreSQL. Forked from https://github.com/iangow/wrds2pg.
Home-page: https://github.com/seanxwzhang/wrds2pg/
Author: Xiaowen Zhang
Author-email: seanxwzhang@gmail.com
License: UNKNOWN
Platform: UNKNOWN
Classifier: Programming Language :: Python :: 3
Classifier: License :: OSI Approved :: MIT License
Classifier: Operating System :: OS Independent
Requires-Python: >=3
